MANIFEST.in
README.md
setup.cfg
setup.py
rta/__init__.py
rta/test.py
rta.egg-info/PKG-INFO
rta.egg-info/SOURCES.txt
rta.egg-info/dependency_links.txt
rta.egg-info/top_level.txt