Metadata-Version: 1.1
Name: rta
Version: 0.0.1
Summary: Retention Time Alignment for LC-IM-MS.
Home-page: https://github.com/MatteoLacki/rta
Author: Mateusz Krzysztof Łącki
Author-email: matteo.lacki@gmail.com
License: UNKNOWN
Keywords: Analitical Chemistry,Mass Spectrometry,Retention Time Alignment
Platform: UNKNOWN
Classifier: Development Status :: 1 - Planning
Classifier: License :: OSI Approved :: BSD License
Classifier: Intended Audience :: Science/Research
Classifier: Topic :: Scientific/Engineering :: Chemistry
Classifier: Programming Language :: Python :: 2.7
Classifier: Programming Language :: Python :: 3.6
